mooquant_okex/__init__.py
mooquant_okex/api.py
mooquant_okex/broker.py
mooquant_okex/common.py
mooquant_okex/livefeed.py
mooquant_okex-0.1.2.dist-info/METADATA
mooquant_okex-0.1.2.dist-info/RECORD
mooquant_okex-0.1.2.dist-info/WHEEL
mooquant_okex-0.1.2.dist-info/entry_points.txt
mooquant_okex-0.1.2.dist-info/top_level.txt
